{
  "card_id": "OGN-048/298",
  "set_code": "Origins",
  "name": "Meditation",
  "cost": 2,
  "might": 0,
  "domain": "Calm",
  "type": "Spell",
  "keywords": [],
  "rules_text": "[Reaction] (Play any time, even before spells and abilities resolve.)As an additional cost to play this, you may exhaust a friendly unit. If you do, draw 2. Otherwise, draw 1.",
  "rarity": "Common",
  "artist": "Kudos Productions",
  "image_url": "https://cmsassets.rgpub.io/sanity/images/dsfx7636/game_data_live/7103336ab0d7f7bebdaa4155e4258d8d9beb06de-744x1039.png"
}